{"life_health.md":"Izd3ASZT","love_think.md":"kuUR6yX9","love_index.md":"tiHZpsvd","think_goal.md":"4GAWYn7_","work_202211.md":"x30CbkCV","theme_team.md":"AU-kk8AY","theme_plan.md":"50t825Rg","work_202310.md":"w-H25PVK","work_index.md":"0yVUvZI7","work_202304.md":"TKAnNx-A","work_202309.md":"IttMQ6GU","theme_api.md":"vyLw71f5","love_marry.md":"zM5YbRk6","index.md":"_SqBrSXf","life_index.md":"_HEOr6u0","work_202302.md":"l5ZWO8lY","work_202308.md":"TZOX9rcQ","work_202401.md":"XBQNB1dJ","child_index.md":"byVlt4ij","work_202305.md":"kFGakVnt","work_202303.md":"USytdZK9","work_202311.md":"KG6b4g-l","think_exe.md":"iCTM3zxK","work_202306.md":"szMxUfKc","think_index.md":"yiuqaJOn","work_seo.md":"JzxDR_Ae","work_202402.md":"HHirAHmF","work_202301.md":"aEsN2Viv","work_202212.md":"mXlykUfe","life_food.md":"YXQzs1aL","theme_index.md":"41SycDJ6","work_202312.md":"j1O4-9KG","work_202307.md":"KfouBjUt","think_cur.md":"KZDr8H8O"}
