{"life_index.md":"BLO9p2YD","index.md":"CeMqgUcr","life_food.md":"DgpROTfx","theme_plan.md":"1BEexJ61","love_index.md":"BmAOS1YQ","think_index.md":"DBWnaulY","love_marry.md":"kZ8YG5n8","theme_index.md":"Cw6sy74f","work_2022_202211.md":"Dc5Un_dx","love_think.md":"CoOtIC16","think_2024_03crawler.md":"BQukx-YM","think_2024_2024goal.md":"DTQH6STr","think_goal.md":"C4WaW3qH","work_2023_202302.md":"RVf3Qxrn","think_2024_02asist.md":"BY45GvD6","child_index.md":"W5CgMQK3","think_exe.md":"Dw6mie3E","theme_api.md":"CUBX9PLM","life_health.md":"3bQK0M7W","work_2024_202402.md":"D-DLjG7l","think_2024_01keepaccounts.md":"JEFQ8wWd","think_cur.md":"B2i6zPwj","theme_team.md":"CkqLo8p4","work_2022_202212.md":"DEQ5e4Rl","work_2023_202311.md":"DWW5_vHw","work_2023_202308.md":"DeiUToT-","work_2024_202406.md":"BLL5Gw57","work_2023_202309.md":"DU9x0wJc","work_2024_202401.md":"BfSK-2hg","work_2023_202310.md":"D-7U96ji","work_2024_202405.md":"CCuGpJQy","work_2024_202403.md":"DB9_wq8p","work_seo.md":"C7NsAie5","work_2023_202312.md":"CmYNAmne","work_index.md":"CigdYYHe","work_2023_202303.md":"BSU4GODM","work_2023_202305.md":"byR8ZbFv","work_2024_202404.md":"DESyiGov","work_2023_202306.md":"BWX6cS-9","work_2023_202304.md":"Bcu4bhMj","work_2023_202307.md":"BIOOzANa","work_2023_202301.md":"-4S3Fnx9"}
