{"work_202211.md":"c3e97a29","theme_plan.md":"52c619a3","theme_team.md":"01cf6eac","think_cur.md":"f8c48471","think_exe.md":"56ecf363","think_goal.md":"815a36e1","think_index.md":"1dd71e9b","life_food.md":"af9d2017","love_marry.md":"7bc34701","life_index.md":"83a9fbd9","theme_api.md":"4337b0c5","index.md":"12733736","work_seo.md":"1d47824a","child_index.md":"c7502b97","work_202312.md":"fe842a2f","work_index.md":"63e41f4e","love_index.md":"89426edd","love_think.md":"6d23bf01","theme_index.md":"9deb418d","work_202311.md":"c7511399","work_202304.md":"d2397889","work_202306.md":"f4309215","work_202303.md":"51d6d9ac","work_202301.md":"66e90ace","work_202305.md":"a7d37803","work_202212.md":"def91b39","work_202307.md":"5c9b5678","work_202302.md":"eeae60d4","work_202309.md":"583ed22d","work_202308.md":"8eaaf0e2","work_202310.md":"07db6637"}
