{"love_marry.md":"aa3e3cbc","theme_api.md":"0d0fa351","theme_plan.md":"5a82f788","theme_team.md":"0e203dc6","think_exe.md":"81eacff6","think_goal.md":"41f3607a","think_index.md":"89e04d87","work_202211.md":"f2dd66b8","work_202301.md":"7694c4aa","think_cur.md":"6454e404","work_202302.md":"9302cd93","love_think.md":"178dc285","theme_index.md":"0c8e3d4d","child_index.md":"d32176cc","hidden_index.md":"8982c05d","index.md":"41e9dac3","life_index.md":"f65a9832","love_index.md":"d039206c","work_202304.md":"06734141","work_202306.md":"13d016d3","work_index.md":"fb08dab2","work_202212.md":"aff4144a","work_202305.md":"e66209c1","work_202303.md":"f00649c6"}
